odoo8_addon_product_pricelist_cache-8.0.1.0.0-py2.7-nspkg.pth
odoo8_addon_product_pricelist_cache-8.0.1.0.0.dist-info/DESCRIPTION.rst
odoo8_addon_product_pricelist_cache-8.0.1.0.0.dist-info/METADATA
odoo8_addon_product_pricelist_cache-8.0.1.0.0.dist-info/RECORD
odoo8_addon_product_pricelist_cache-8.0.1.0.0.dist-info/WHEEL
odoo8_addon_product_pricelist_cache-8.0.1.0.0.dist-info/metadata.json
odoo8_addon_product_pricelist_cache-8.0.1.0.0.dist-info/namespace_packages.txt
odoo8_addon_product_pricelist_cache-8.0.1.0.0.dist-info/top_level.txt
odoo_addons/product_pricelist_cache/README.rst
odoo_addons/product_pricelist_cache/__init__.py
odoo_addons/product_pricelist_cache/__openerp__.py
odoo_addons/product_pricelist_cache/data/product_price_cache_cron.xml
odoo_addons/product_pricelist_cache/models/__init__.py
odoo_addons/product_pricelist_cache/models/product_price_cache.py
odoo_addons/product_pricelist_cache/models/product_pricelist.py
odoo_addons/product_pricelist_cache/security/ir.model.access.csv
odoo_addons/product_pricelist_cache/static/description/icon.png
odoo_addons/product_pricelist_cache/tests/__init__.py
odoo_addons/product_pricelist_cache/tests/test_product_price_cache.py
odoo_addons/product_pricelist_cache/views/product_price_cache.xml
